README.txt
setup.cfg
setup.py
collective/__init__.py
collective.kss.inlinejs.egg-info/PKG-INFO
collective.kss.inlinejs.egg-info/SOURCES.txt
collective.kss.inlinejs.egg-info/dependency_links.txt
collective.kss.inlinejs.egg-info/entry_points.txt
collective.kss.inlinejs.egg-info/namespace_packages.txt
collective.kss.inlinejs.egg-info/not-zip-safe
collective.kss.inlinejs.egg-info/requires.txt
collective.kss.inlinejs.egg-info/top_level.txt
collective/kss/__init__.py
collective/kss/inlinejs/__init__.py
collective/kss/inlinejs/collective.kss.inlinejs-configure.zcml
collective/kss/inlinejs/commands.py
collective/kss/inlinejs/configure.zcml
collective/kss/inlinejs/interfaces.py
collective/kss/inlinejs/demo/__init__.py
collective/kss/inlinejs/demo/configure.zcml
collective/kss/inlinejs/demo/inlinejs.kss
collective/kss/inlinejs/demo/inlinejs.pt
collective/kss/inlinejs/demo/zopeconfig.py
collective/kss/inlinejs/javascript/inlinejs.js
collective/kss/inlinejs/javascript/plugin.js
collective/kss/inlinejs/tests/__init__.py
docs/HISTORY.txt