Metadata-Version: 1.0
Name: collective.kss.inlinejs
Version: 1.0
Summary: Plugin that allows you to put javascript code evaluated by kss
Home-page: http://www.redomino.com
Author: Davide Moro
Author-email: davide.moro@redomino.com
License: GPL
Keywords: kss plugin
Platform: UNKNOWN
Classifier: Framework :: Plone
Classifier: Framework :: Zope2
Classifier: Framework :: Zope3
Classifier: Programming Language :: Python
Classifier: Topic :: Software Development :: Libraries :: Python Modules
